[
  {
    "title": "The Art of Living",
    "author": "Epictetus",
    "image": "/images/epictetus.jpeg",
    "description": "A guide to the Stoic philosophy of Epictetus on how to live a good life."
  },
  {
    "title": "The Prince",
    "author": "Niccolò Machiavelli",
    "image": "/images/prince.jpg",
    "description": "A political treatise on how to acquire and maintain political power."
  },
  {
    "title": "The Story of Philosophy",
    "author": "Will Durant",
    "image": "/images/philosophy.jpg",
    "description": "The classic account of the lives and opinions of the great philosophers of the western world—from Plato to Santayana."
  }
]
